Workbook
Name aporte: Calculos!$D$13
Name patrimonio: Calculos!$D$16
Name qtd_anos: Calculos!$D$14
Name red_carteira: Calculos!$D$9
Name salario: Calculos!$D$8
Name tax_mensal: Calculos!$D$15

Sheet Calculos
B7: CONFIGURAÇÕES
B8: Salário | D8: 2000
B9: Rendimento Carteira | D9: 0.01079
B10: Sugestão de Investimento (30%) | D10: =salario*30% -> 600
B12: INVESTIMENTO MENSAL
B13: Quanto investir por mês ? | D13: 500
B14: Por Quantos Anos ? | D14: 5
B15: Taxa de Rendimento mensal ? | D15: 0.01079
B16: Patrimônio acumulado ? | D16: =FV(tax_mensal,qtd_anos*12,aporte*-1) -> 41888.457
B17: Dividendos Mensais ? | D17: =patrimonio*red_carteira -> 451.97645
B19: CENÁRIOS | D19: Dividendo
A20: 2 | B20: Quanto em 2 Anos ? | C20: =FV($D$15,$A20*12,$D$13*-1) -> 13613.814 | D20: =C20*red_carteira -> 146.89305
A21: 5 | B21: Quanto em 5 Anos ? | C21: =FV($D$15,$A21*12,$D$13*-1) -> 41888.457 | D21: =C21*red_carteira -> 451.97645
A22: 10 | B22: Quanto em 10 Anos ? | C22: =FV($D$15,$A22*12,$D$13*-1) -> 121642.11 | D22: =C22*red_carteira -> 1312.5183
A23: 20 | B23: Quanto em 20 Anos ? | C23: =FV($D$15,$A23*12,$D$13*-1) -> 562599.2 | D23: =C23*red_carteira -> 6070.4454
A24: 30 | B24: Quanto em 30 Anos ? | C24: =FV($D$15,$A24*12,$D$13*-1) -> 2161084.8 | D24: =C24*red_carteira -> 23318.105
B27: PERFIL | D27: Conservador
B28: VALOR A SER INVESTIDO POR MÊS | D28: =aporte -> 500
B30: TIPO DE FII | C30: Percentual Sugerido | D30: Valores
B31: PAPEL | C31: =VLOOKUP($D$27&"-"&B31,BD!$A:$D,4,FALSE) -> 0.3 | D31: =$D$28*C31 -> 150
B32: TIJOLO | C32: =VLOOKUP($D$27&"-"&B32,BD!$A:$D,4,FALSE) -> 0.5 | D32: =$D$28*C32 -> 250
B33: HÍBRIDOS | C33: =VLOOKUP($D$27&"-"&B33,BD!$A:$D,4,FALSE) -> 0.1 | D33: =$D$28*C33 -> 50
B34: FOFs | C34: =VLOOKUP($D$27&"-"&B34,BD!$A:$D,4,FALSE) -> 0.1 | D34: =$D$28*C34 -> 50
B35: DESENVOLVIMENTO | C35: =VLOOKUP($D$27&"-"&B35,BD!$A:$D,4,FALSE) -> 0 | D35: =$D$28*C35 -> 0
B36: HOTELARIAS | C36: =VLOOKUP($D$27&"-"&B36,BD!$A:$D,4,FALSE) -> 0 | D36: =$D$28*C36 -> 0
D37: =SUM(D31:D36) -> 500

Sheet BD
A2: CHAVE ÚNICA | B2: PERFIL | C2: TIPO DE FII | D2: %
A3: Conservador-PAPEL | B3: Conservador | C3: PAPEL | D3: 0.3
A4: Conservador-TIJOLO | B4: Conservador | C4: TIJOLO | D4: 0.5
A5: Conservador-HÍBRIDOS | B5: Conservador | C5: HÍBRIDOS | D5: 0.1
A6: Conservador-FOFs | B6: Conservador | C6: FOFs | D6: 0.1
A7: Conservador-DESENVOLVIMENTO | B7: Conservador | C7: DESENVOLVIMENTO | D7: 0
A8: Conservador-HOTELARIAS | B8: Conservador | C8: HOTELARIAS | D8: 0
A9: Moderado-PAPEL | B9: Moderado | C9: PAPEL | D9: 0.32
A10: Moderado-TIJOLO | B10: Moderado | C10: TIJOLO | D10: 0.35
A11: Moderado-HÍBRIDOS | B11: Moderado | C11: HÍBRIDOS | D11: 0.08
A12: Moderado-FOFs | B12: Moderado | C12: FOFs | D12: 0.05
A13: Moderado-DESENVOLVIMENTO | B13: Moderado | C13: DESENVOLVIMENTO | D13: 0.1
A14: Moderado-HOTELARIAS | B14: Moderado | C14: HOTELARIAS | D14: 0.1
... A20: Agressivo-HOTELARIAS | B20: Agressivo | C20: HOTELARIAS | D20: 0.1
